armada_microservice-0.0.1.data/scripts/microservice
armada_microservice-0.0.1.dist-info/DESCRIPTION.rst
armada_microservice-0.0.1.dist-info/METADATA
armada_microservice-0.0.1.dist-info/RECORD
armada_microservice-0.0.1.dist-info/WHEEL
armada_microservice-0.0.1.dist-info/metadata.json
armada_microservice-0.0.1.dist-info/top_level.txt
microservice/__init__.py
microservice/armada_agent.py
microservice/bootstrap_microservice.py
microservice/register_in_service_discovery.py
microservice/run_hooks.py
microservice/save_environment_variables.py
microservice/version.py
microservice/common/__init__.py
microservice/common/consul.py
microservice/common/docker_client.py
microservice/common/service_discovery.py
microservice/local_magellan/__init__.py
microservice/local_magellan/haproxy.py
microservice/local_magellan/local_magellan.py
microservice/local_magellan/require_service.py
