Metadata-Version: 2.0
Name: armada-microservice
Version: 0.0.1
Summary: Microservice package - base of all armada microservices. CLI for communicating between microservice and armada.
Home-page: https://github.com/armadaplatform/armada-microservice
Author: Cerebro
Author-email: cerebro@ganymede.eu
License: UNKNOWN
Platform: UNKNOWN
Requires-Dist: docker (==2.4.2)
Requires-Dist: requests (==2.9.1)
Requires-Dist: armada
